fastapi_proxy/__init__.py
fastapi_proxy/core.py
fastapi_proxy/network.py
fastapi_proxy/requirements.txt
fastapi_proxy/utils/__init__.py
fastapi_proxy/utils/body.py
fastapi_proxy/utils/form.py
fastapi_proxy/utils/headers.py
fastapi_proxy/utils/query.py
fastapi_proxy/utils/request.py
fastapi_proxy/utils/response.py
tests/__init__.py
tests/conftest.py
tests/test_gateway.py
tests/fastapi_microservice/__init__.py
tests/fastapi_microservice/main.py
tests/fastapi_microservice/models.py
tests/fastapi_microservice/images/__init__.py
tests/src/__init__.py
fastapi_proxy-0.103.1.0.dist-info/LICENSE
fastapi_proxy-0.103.1.0.dist-info/METADATA
fastapi_proxy-0.103.1.0.dist-info/WHEEL
fastapi_proxy-0.103.1.0.dist-info/top_level.txt
fastapi_proxy-0.103.1.0.dist-info/RECORD
