Metadata-Version: 2.1
Name: fastapi-proxy
Version: 0.103.1.0
Summary: FastAPI Proxy
Home-page: https://github.com/cedvict/fastapi-proxy
Author: Cedvict Loknov
Author-email: Cedvict Loknov <cedvict@gmail.com>
Maintainer-email: Cedvict Loknov <cedvict@gmail.com>
Project-URL: Documentation, https://fastapi-proxy.nnenu.com/
Keywords: FastAPI,Proxy,Gateway,Microservice
Classifier: Development Status :: 3 - Alpha
Classifier: Intended Audience :: Developers
Classifier: Topic :: Internet :: WWW/HTTP :: Session
Classifier: Topic :: Internet :: WWW/HTTP :: WSGI
Classifier: Topic :: Software Development :: Libraries :: Application Frameworks
Classifier: Topic :: Software Development :: Libraries :: Python Modules
Classifier: Framework :: FastAPI
Classifier: License :: OSI Approved :: Apache Software License
Classifier: Programming Language :: Python :: 3.8
Requires-Python: >=3.10
License-File: LICENSE
Requires-Dist: aiohttp >=3.7.1
Requires-Dist: fastapi >=0.103.1
Requires-Dist: pydantic ==1.8.2
Requires-Dist: python-multipart ==0.0.6
Requires-Dist: ujson >=5.8.0
